brisk/__init__.py
brisk/funcs.py
brisk-0.1.dist-info/WHEEL
brisk-0.1.dist-info/RECORD
brisk-0.1.dist-info/DESCRIPTION.rst
brisk-0.1.dist-info/metadata.json
brisk-0.1.dist-info/top_level.txt
brisk-0.1.dist-info/METADATA
