Metadata-Version: 2.0
Name: brisk
Version: 0.1
Summary: Fast implementation of numerical functions using Numba
Home-page: https://github.com/David-OConnor/brisk
Author: David O'Connor
Author-email: david.alan.oconnor@gmail.com
License: Apache
Keywords: fast,numba,numerical,optimized
Platform: UNKNOWN
Requires-Dist: numba (>=0.17.0)
Requires-Dist: numpy (>=1.9.1)
